pcol.py
pcol-0.2.0.dist-info/DESCRIPTION.rst
pcol-0.2.0.dist-info/METADATA
pcol-0.2.0.dist-info/metadata.json
pcol-0.2.0.dist-info/RECORD
pcol-0.2.0.dist-info/top_level.txt
pcol-0.2.0.dist-info/WHEEL
