Metadata-Version: 2.0
Name: pcol
Version: 0.2.0
Summary: A straightforward color rendering library for Python
Home-page: https://github.com/jcomo/pcol
Author: Jonathan Como
Author-email: jonathan.como@gmail.com
License: UNKNOWN
Keywords: console terminal color tree
Platform: UNKNOWN
Classifier: Programming Language :: Python :: 2
Classifier: Programming Language :: Python :: 2.6
Classifier: Programming Language :: Python :: 2.7
